{
  "count": 6,
  "data": [
    {
      "city": "Manisa",
      "district": "YUNUSEMRE",
      "neighborhoods": [
        "AKMESCİT"
      ],
      "description": "ANA BORU BİRLEŞİMİ Sebebiyle Su Kesintisi",
      "start": "27.04.2026 11:37",
      "end": "27.04.2026 12:37"
    },
    {
      "city": "Manisa",
      "district": "AKHİSAR",
      "neighborhoods": [
        "HACI İSHAK",
        "HÜRRİYET"
      ],
      "description": "ANA ŞEBEKE ARIZASI Sebebiyle Su Kesintisi",
      "start": "27.04.2026 11:23",
      "end": "27.04.2026 13:23"
    },
    {
      "city": "Manisa",
      "district": "ALAŞEHİR",
      "neighborhoods": [
        "FATİH",
        "HACIBEY",
        "SAKARYA"
      ],
      "description": "ANA ŞEBEKE ARIZASI Sebebiyle Su Kesintisi",
      "start": "27.04.2026 11:07",
      "end": "27.04.2026 13:10"
    },
    {
      "city": "Manisa",
      "district": "YUNUSEMRE",
      "neighborhoods": [
        "FATİH",
        "HAFSA SULTAN"
      ],
      "description": "ANA BORU BİRLEŞİMİ Sebebiyle Su Kesintisi",
      "start": "27.04.2026 10:23",
      "end": "Süre Verilememekte"
    },
    {
      "city": "Manisa",
      "district": "YUNUSEMRE",
      "neighborhoods": [
        "AKGEDİK"
      ],
      "description": "ANA BORU BİRLEŞİMİ Sebebiyle Su Kesintisi",
      "start": "27.04.2026 09:31",
      "end": "Süre Verilememekte"
    },
    {
      "city": "Manisa",
      "district": "AKHİSAR",
      "neighborhoods": [
        "EFENDİ",
        "KETHÜDA",
        "REŞAT BEY",
        "SEYİT AHMET",
        "ULU CAMİİ"
      ],
      "description": "ANA ŞEBEKE ARIZASI Sebebiyle Su Kesintisi",
      "start": "27.04.2026 08:53",
      "end": "27.04.2026 12:53"
    }
  ]
}