{
  "count": 12,
  "data": [
    {
      "city": "Manisa",
      "district": "ŞEHZADELER",
      "neighborhoods": [
        "NİŞANCIPAŞA"
      ],
      "description": "BORU PATLAĞI Sebebiyle Su Kesintisi",
      "start": "28.01.2026 08:17",
      "end": "Süre Verilememekte"
    },
    {
      "city": "Manisa",
      "district": "AKHİSAR",
      "neighborhoods": [
        "ATATÜRK",
        "CUMHURİYET",
        "EFENDİ",
        "HACI İSHAK",
        "HAS HOCA",
        "HÜRRİYET",
        "İNÖNÜ",
        "KETHÜDA",
        "PAŞA",
        "RAGIP BEY",
        "REŞAT BEY",
        "SEYİT AHMET",
        "ULU CAMİİ",
        "ŞEYHİSA"
      ],
      "description": "HAT BAKIM ONARIMI Sebebiyle Su Kesintisi",
      "start": "27.01.2026 18:01",
      "end": "28.01.2026 08:45"
    },
    {
      "city": "Manisa",
      "district": "YUNUSEMRE",
      "neighborhoods": [
        "BARBAROS"
      ],
      "description": "BORU PATLAĞI Sebebiyle Su Kesintisi",
      "start": "28.01.2026 09:24",
      "end": "28.01.2026 10:24"
    },
    {
      "city": "Manisa",
      "district": "ŞEHZADELER",
      "neighborhoods": [
        "ADAKALE",
        "BAYINDIRLIK",
        "GEDİZ",
        "İSHAKÇELEBI",
        "KOCATEPE"
      ],
      "description": "BORU PATLAĞI Sebebiyle Su Kesintisi",
      "start": "27.01.2026 13:54",
      "end": "28.01.2026 08:19"
    },
    {
      "city": "Manisa",
      "district": "KIRKAĞAÇ",
      "neighborhoods": [
        "BOSTANCI"
      ],
      "description": "DEPO BAKIMI VE ONARIMI Sebebiyle Su Kesintisi",
      "start": "27.01.2026 15:00",
      "end": "27.01.2026 17:00"
    },
    {
      "city": "Manisa",
      "district": "AKHİSAR",
      "neighborhoods": [
        "ULU CAMİİ"
      ],
      "description": "BORU PATLAĞI Sebebiyle Su Kesintisi",
      "start": "28.01.2026 10:20",
      "end": "28.01.2026 12:20"
    },
    {
      "city": "Manisa",
      "district": "YUNUSEMRE",
      "neighborhoods": [
        "AYNİ ALİ",
        "KUYUALAN",
        "TOPÇUASIM"
      ],
      "description": "BORU PATLAĞI Sebebiyle Su Kesintisi",
      "start": "27.01.2026 15:28",
      "end": "27.01.2026 16:00"
    },
    {
      "city": "Manisa",
      "district": "YUNUSEMRE",
      "neighborhoods": [
        "AYNİ ALİ",
        "KUYUALAN"
      ],
      "description": "BORU PATLAĞI Sebebiyle Su Kesintisi",
      "start": "27.01.2026 14:03",
      "end": "27.01.2026 15:03"
    },
    {
      "city": "Manisa",
      "district": "KULA",
      "neighborhoods": [
        "4 EYLÜL"
      ],
      "description": "ANA BORU BİRLEŞİMİ Sebebiyle Su Kesintisi",
      "start": "28.01.2026 09:37",
      "end": "Süre Verilememekte"
    },
    {
      "city": "Manisa",
      "district": "ALAŞEHİR",
      "neighborhoods": [
        "FATİH",
        "HACIBEY",
        "SAKARYA"
      ],
      "description": "BORU PATLAĞI Sebebiyle Su Kesintisi",
      "start": "27.01.2026 12:26",
      "end": "27.01.2026 13:30"
    },
    {
      "city": "Manisa",
      "district": "ALAŞEHİR",
      "neighborhoods": [
        "FATİH",
        "HACIBEY",
        "SAKARYA"
      ],
      "description": "BORU PATLAĞI Sebebiyle Su Kesintisi",
      "start": "27.01.2026 16:50",
      "end": "27.01.2026 18:00"
    },
    {
      "city": "Manisa",
      "district": "ALAŞEHİR",
      "neighborhoods": [
        "SOĞANLI"
      ],
      "description": "GEDİZ ELEKTRİK AŞ BAKIM ONARIM ÇALIŞMASI Sebebiyle Su Kesintisi",
      "start": "27.01.2026 14:58",
      "end": "27.01.2026 23:00"
    }
  ]
}