{
  "count": 3,
  "data": [
    {
      "city": "Manisa",
      "district": "KÖPRÜBAŞI",
      "neighborhoods": [
        "GÜLPINAR"
      ],
      "description": "HAT BAKIM ONARIMI Sebebiyle Su Kesintisi",
      "start": "05.03.2026 21:10",
      "end": "Süre Verilememekte"
    },
    {
      "city": "Manisa",
      "district": "YUNUSEMRE",
      "neighborhoods": [
        "AKGEDİK"
      ],
      "description": "ANA BORU BİRLEŞİMİ Sebebiyle Su Kesintisi",
      "start": "05.03.2026 20:53",
      "end": "Süre Verilememekte"
    },
    {
      "city": "Manisa",
      "district": "AKHİSAR",
      "neighborhoods": [
        "ATATÜRK",
        "CUMHURİYET",
        "HACI İSHAK",
        "HAS HOCA",
        "HÜRRİYET",
        "İNÖNÜ",
        "PAŞA",
        "RAGIP BEY"
      ],
      "description": "HAT BAKIM ONARIMI Sebebiyle Su Kesintisi",
      "start": "05.03.2026 20:30",
      "end": "06.03.2026 05:00"
    }
  ]
}