{
  "count": 2,
  "data": [
    {
      "city": "Manisa",
      "district": "TURGUTLU",
      "neighborhoods": [
        "ERGENEKON"
      ],
      "description": "ANA ŞEBEKE ARIZASI Sebebiyle Su Kesintisi",
      "start": "23.03.2026 15:29",
      "end": "Süre Verilememekte"
    },
    {
      "city": "Manisa",
      "district": "ALAŞEHİR",
      "neighborhoods": [
        "BEŞEYLÜL",
        "FATİH",
        "HACIBEY",
        "İSTASYON",
        "KURTULUŞ",
        "SAKARYA",
        "SARISU",
        "SOĞUKSU",
        "YENİ",
        "YENİCE"
      ],
      "description": "ANA ŞEBEKE ARIZASI Sebebiyle Su Kesintisi",
      "start": "23.03.2026 15:06",
      "end": "23.03.2026 18:06"
    }
  ]
}